openrepos
