Metadata-Version: 2.1
Name: openrepos-webclient
Version: 1.1.0
Summary: OpenRepos.net web client
Home-page: UNKNOWN
Author: Yann Buechau
Author-email: nobodyinperson@posteo.de
License: GPLv3
Keywords: openrepos,openrepos.net,sailfish,sailfishos,selenium,firefox,xvfb
Platform: UNKNOWN
Classifier: License :: OSI Approved :: GNU General Public License v3 (GPLv3)
Classifier: Programming Language :: Python :: 3.8
Classifier: Programming Language :: Python :: 3.7
Classifier: Programming Language :: Python :: 3.6
Classifier: Programming Language :: Python :: 3.5
